dockloader/__init__.py
dockloader/attribute.py
dockloader/cmds/__init__.py
dockloader/cmds/config.py
dockloader/cmds/images.py
dockloader/dockhub/__init__.py
dockloader/dockhub/tags.py
dockloader/utils/__init__.py
dockloader/utils/docker.py
dockloader/utils/docker_hub.py
dockloader/utils/tags.py
dockloader-0.2.dist-info/LICENSE
dockloader-0.2.dist-info/METADATA
dockloader-0.2.dist-info/WHEEL
dockloader-0.2.dist-info/entry_points.txt
dockloader-0.2.dist-info/top_level.txt
dockloader-0.2.dist-info/zip-safe
dockloader-0.2.dist-info/RECORD
